[
  {
    "id": 1,
    "name": "Jaket Casual Jakmania — Edition Merah Betawi",
    "price": "Rp 385.000",
    "image": "https://images.unsplash.com/photo-1520975954732-35dd22299614?q=80&w=600&auto=format&fit=crop",
    "tag": "New Drop",
    "color": "#CC0000",
    "categories": ["casuals", "jakarta", "new"],
    "details": "Jaket casual tebal dengan motif batik Betawi dan identitas supporter Jakarta. Limited edition. Bahan fleece premium 300gsm, sablon discharge tahan lama.",
    "linktreeUrl": "https://linktr.ee/ultrasid"
  },
  {
    "id": 2,
    "name": "Hoodie Ultraviolent — Bobotoh Edition",
    "price": "Rp 425.000",
    "originalPrice": "Rp 500.000",
    "image": "https://images.unsplash.com/photo-1556821840-3a63f15732ce?q=80&w=600&auto=format&fit=crop",
    "tag": "Diskon 15%",
    "color": "#003087",
    "categories": ["hooligans", "bandung", "new", "sale"],
    "details": "Hoodie tebal dengan grafis tribal Sunda dan identitas Bobotoh. Bahan cotton fleece 350gsm, potongan oversized, cocok untuk tribun dan jalanan.",
    "linktreeUrl": "https://linktr.ee/ultrasid"
  },
  {
    "id": 3,
    "name": "Bomber Jacket — Singo Edan Aremania",
    "price": "Rp 545.000",
    "image": "https://images.unsplash.com/photo-1591047139829-d91aecb6caea?q=80&w=600&auto=format&fit=crop",
    "tag": "Eksklusif",
    "color": "#1E4DB7",
    "categories": ["casuals", "malang", "new"],
    "details": "Bomber jacket premium dengan sulaman logo Arema dan elemen grafis tribal Jawa Timur. Bahan twill water-resistant.",
    "linktreeUrl": "https://linktr.ee/ultrasid"
  },
  {
    "id": 4,
    "name": "Crewneck Ultras — LA Mania Makasar",
    "price": "Rp 315.000",
    "image": "https://images.unsplash.com/photo-1620799140408-edc6dcb6d633?q=80&w=600&auto=format&fit=crop",
    "tag": "Hot",
    "color": "#E31837",
    "categories": ["casuals", "sulawesi", "sale"],
    "details": "Crewneck oversized dengan grafis batik Makassar. Simbol persatuan supporter Sulawesi Selatan. Cotton combed 30s premium.",
    "linktreeUrl": "https://linktr.ee/ultrasid"
  },
  {
    "id": 5,
    "name": "Cargo Pants — Street Hooligan Series",
    "price": "Rp 385.000",
    "image": "https://images.unsplash.com/photo-1542272454315-4c01d7abdf4a?q=80&w=600&auto=format&fit=crop",
    "color": "#1a1a1a",
    "categories": ["hooligans", "new"],
    "details": "Celana cargo tactical dengan bahan ripstop kuat. Desain fungsional dengan banyak kantong. Inspirasi dari kultur hooligan Inggris.",
    "linktreeUrl": "https://linktr.ee/ultrasid"
  },
  {
    "id": 6,
    "name": "Tee Oversized — Tribal Minang Semen Padang",
    "price": "Rp 220.000",
    "image": "https://images.unsplash.com/photo-1583743814966-8936f5b7be1a?q=80&w=600&auto=format&fit=crop",
    "color": "#FFD700",
    "categories": ["casuals", "sumatra", "new"],
    "details": "Kaos oversized dengan motif tenun Minangkabau dipadukan identitas supporter Semen Padang. Bahan cotton bambu 200gsm.",
    "linktreeUrl": "https://linktr.ee/ultrasid"
  },
  {
    "id": 7,
    "name": "Track Jacket — PSPS Pekanbaru Pride",
    "price": "Rp 465.000",
    "image": "https://images.unsplash.com/photo-1594938298603-21023e2aa3b4?q=80&w=600&auto=format&fit=crop",
    "tag": "Populer",
    "color": "#E60026",
    "categories": ["casuals", "sumatra"],
    "details": "Track jacket retro dengan aksen motif melayu dan identitas supporter Riau. Bahan polyester milky berkualitas dengan bordir premium.",
    "linktreeUrl": "https://linktr.ee/ultrasid"
  },
  {
    "id": 8,
    "name": "Coach Jacket — Suporter Bali United",
    "price": "Rp 495.000",
    "image": "https://images.unsplash.com/photo-1601063467369-5c3ad86f600c?q=80&w=600&auto=format&fit=crop",
    "tag": "Baru",
    "color": "#FF4500",
    "categories": ["casuals", "bali", "new"],
    "details": "Coach jacket dengan ukiran motif Barong Bali dipadukan identitas supporter Bali United. Water resistant, vivid print sublimasi.",
    "linktreeUrl": "https://linktr.ee/ultrasid"
  },
  {
    "id": 9,
    "name": "Parka Hoodie — Persebaya Green Force",
    "price": "Rp 575.000",
    "originalPrice": "Rp 650.000",
    "image": "https://images.unsplash.com/photo-1551698618-1dfe5d97d256?q=80&w=600&auto=format&fit=crop",
    "tag": "Diskon 12%",
    "color": "#00AA00",
    "categories": ["hooligans", "jawa", "sale"],
    "details": "Parka hoodie tebal dengan grafis batik Surabaya dan elemen Green Force Bonek. Bahan canvas premium waterproof.",
    "linktreeUrl": "https://linktr.ee/ultrasid"
  },
  {
    "id": 10,
    "name": "Bucket Hat — Casual Ultras Series",
    "price": "Rp 165.000",
    "image": "https://images.unsplash.com/photo-1534215754734-18e55d13e346?q=80&w=600&auto=format&fit=crop",
    "tag": "Aksesoris",
    "color": "#333333",
    "categories": ["casuals", "accessories", "new"],
    "details": "Bucket hat dengan embroidery skema supporter Indonesia. Bahan canvas 6-panel, adjustable strap.",
    "linktreeUrl": "https://linktr.ee/ultrasid"
  }
]